{
    "id": 388,
    "step": 387,
    "round": 1,
    "stage": "1-387",
    "info": {
        "env_time": 408.5000000000586,
        "red_wins": 0,
        "blue_wins": 0,
        "draw": 0,
        "reward": 0,
        "time": 408.5000000000586
    },
    "tree": {
        "tag": "Sequence",
        "children": [
            {
                "tag": "FollowRoute",
                "children": [],
                "data": {
                    "id": "dbdc99d195864132998bb995263676d4",
                    "status": "SUCCESS",
                    "type": "action",
                    "tag": "FollowRoute",
                    "feedback_message": "",
                    "name": "FollowRoute",
                    "children_count": 0,
                    "_reset_count": 1,
                    "_initialise_count": 388,
                    "_tick_count": 388,
                    "_update_count": 0,
                    "_terminate_count": 388,
                    "actions": [
                        "(<Actions.go_to_location: 1>, -10000, 10000)"
                    ],
                    "agent_name": "blue_1",
                    "update_messages": [],
                    "route": [
                        "[-10000, -10000]",
                        "[-10000, 10000]",
                        "[10000, 10000]",
                        "[10000, -10000]"
                    ],
                    "route_index": 1,
                    "recursive": true,
                    "agent": {
                        "name": "blue_1",
                        "type": "aircraft",
                        "color": "blue",
                        "speed": 222,
                        "turn_radius": 558.7755102040816,
                        "collision_radius": 10,
                        "x": -8959.375948564682,
                        "y": 10455.2790698493,
                        "psi": 156.73918359799222,
                        "destroyed": false,
                        "destroyed_reason": "",
                        "route": 926,
                        "route_index": 459,
                        "waiting_actions": [],
                        "consumed_actions": [
                            "(399, (<Actions.go_to_location: 1>, -10000, 10000))",
                            "(400, (<Actions.go_to_location: 1>, -10000, 10000))",
                            "(401, (<Actions.go_to_location: 1>, -10000, 10000))",
                            "(402, (<Actions.go_to_location: 1>, -10000, 10000))",
                            "(403, (<Actions.go_to_location: 1>, -10000, 10000))",
                            "(404, (<Actions.go_to_location: 1>, -10000, 10000))",
                            "(405, (<Actions.go_to_location: 1>, -10000, 10000))",
                            "(406, (<Actions.go_to_location: 1>, -10000, 10000))",
                            "(407, (<Actions.go_to_location: 1>, -10000, 10000))",
                            "(408, (<Actions.go_to_location: 1>, -10000, 10000))"
                        ],
                        "missile_count": 10,
                        "fuel": 1391.5000000003715,
                        "fuel_consumption_rate": 1,
                        "radar_radius": 10000.0,
                        "missile_destroyed_enemies": []
                    }
                }
            }
        ],
        "data": {
            "id": "ca060f686aee4f0e8b670cb6f30b827b",
            "status": "SUCCESS",
            "type": "action",
            "tag": "Sequence",
            "feedback_message": "",
            "name": "Sequence",
            "children_count": 1,
            "_reset_count": 1,
            "_initialise_count": 0,
            "_tick_count": 388,
            "_update_count": 0,
            "_terminate_count": 0
        }
    }
}