{
    "id": 2960,
    "step": 307,
    "round": 4,
    "stage": "4-307",
    "info": {
        "env_time": 328.5000000000404,
        "red_wins": 0,
        "blue_wins": 0,
        "draw": 3,
        "reward": 0,
        "time": 328.5000000000404
    },
    "tree": {
        "tag": "Sequence",
        "children": [
            {
                "tag": "FollowRoute",
                "children": [],
                "data": {
                    "id": "a20a38481b7842afb08ab840e50486bc",
                    "status": "SUCCESS",
                    "type": "action",
                    "tag": "FollowRoute",
                    "feedback_message": "",
                    "name": "FollowRoute",
                    "children_count": 0,
                    "_reset_count": 4,
                    "_initialise_count": 2960,
                    "_tick_count": 2960,
                    "_update_count": 0,
                    "_terminate_count": 2960,
                    "actions": [
                        "(<Actions.go_to_location: 1>, 10000, 10000)"
                    ],
                    "agent_name": "red_1",
                    "update_messages": [],
                    "route": [
                        "[-10000, -10000]",
                        "[-10000, 10000]",
                        "[10000, 10000]",
                        "[10000, -10000]"
                    ],
                    "route_index": 2,
                    "recursive": true,
                    "agent": {
                        "name": "red_1",
                        "type": "aircraft",
                        "color": "red",
                        "speed": 222,
                        "turn_radius": 558.7755102040816,
                        "collision_radius": 10,
                        "x": 5812.239496689273,
                        "y": 9997.995456695666,
                        "psi": 89.97257439571172,
                        "destroyed": false,
                        "destroyed_reason": "",
                        "route": 1796,
                        "route_index": 1419,
                        "waiting_actions": [],
                        "consumed_actions": [
                            "(319, (<Actions.go_to_location: 1>, 10000, 10000))",
                            "(320, (<Actions.go_to_location: 1>, 10000, 10000))",
                            "(321, (<Actions.go_to_location: 1>, 10000, 10000))",
                            "(322, (<Actions.go_to_location: 1>, 10000, 10000))",
                            "(323, (<Actions.go_to_location: 1>, 10000, 10000))",
                            "(324, (<Actions.go_to_location: 1>, 10000, 10000))",
                            "(325, (<Actions.go_to_location: 1>, 10000, 10000))",
                            "(326, (<Actions.go_to_location: 1>, 10000, 10000))",
                            "(327, (<Actions.go_to_location: 1>, 10000, 10000))",
                            "(328, (<Actions.go_to_location: 1>, 10000, 10000))"
                        ],
                        "missile_count": 10,
                        "fuel": 1471.5000000002988,
                        "fuel_consumption_rate": 1,
                        "radar_radius": 10000.0,
                        "missile_destroyed_enemies": []
                    }
                }
            }
        ],
        "data": {
            "id": "e1665182f17a4d3eaea3db8146d850e2",
            "status": "SUCCESS",
            "type": "action",
            "tag": "Sequence",
            "feedback_message": "",
            "name": "Sequence",
            "children_count": 1,
            "_reset_count": 4,
            "_initialise_count": 0,
            "_tick_count": 2960,
            "_update_count": 0,
            "_terminate_count": 0
        }
    }
}